LICENSE
README.md
setup.py
makit/lib/__init__.py
makit/lib/_decorators.py
makit/lib/_event.py
makit/lib/_input.py
makit/lib/_time.py
makit/lib/attr.py
makit/lib/cnholiday.py
makit/lib/command.py
makit/lib/config.py
makit/lib/const.py
makit/lib/ctx.py
makit/lib/encoding.py
makit/lib/errors.py
makit/lib/hook.py
makit/lib/network.py
makit/lib/ospath.py
makit/lib/py.py
makit/lib/query.py
makit/lib/string.py
makit/lib/sysutil.py
makit/lib/task.py
makit/lib/validate.py
makit/lib/inspect/__init__.py
makit/lib/inspect/_common.py
makit/lib/inspect/_method.py
makit/lib/json/__init__.py
makit/lib/json/_base.py
makit/lib/json/decode.py
makit/lib/json/encode.py
makit/lib/json/lookup.py
makit/lib/samples/__init__.py
makit/lib/samples/command_sample.py
makit/lib/samples/event_sample.py
makit/lib/samples/inspect_sample.py
makit/lib/samples/json_sample.py
makit/lib/samples/ospath_sample.py
makit/lib/samples/query_sample.py
makitdone_lib.egg-info/PKG-INFO
makitdone_lib.egg-info/SOURCES.txt
makitdone_lib.egg-info/dependency_links.txt
makitdone_lib.egg-info/requires.txt
makitdone_lib.egg-info/top_level.txt