Metadata-Version: 2.4
Name: makitdone-lib
Version: 2.0.3
Summary: python基础库扩展
Home-page: https://gitee.com/makitdone/makitdone-lib
Author: liangchao
Author-email: liang20201101@163.com
License: MIT
Requires-Python: >=3.3
License-File: LICENSE
Requires-Dist: docstring_parser~=0.17.0
Requires-Dist: psutil~=7.1.1
Requires-Dist: setuptools~=80.9.0
Dynamic: author
Dynamic: author-email
Dynamic: home-page
Dynamic: license
Dynamic: license-file
Dynamic: requires-dist
Dynamic: requires-python
Dynamic: summary
